mycalc/calculator.py
cheonscalculator-0.0.1.dist-info/LICENSE
cheonscalculator-0.0.1.dist-info/METADATA
cheonscalculator-0.0.1.dist-info/WHEEL
cheonscalculator-0.0.1.dist-info/top_level.txt
cheonscalculator-0.0.1.dist-info/RECORD
