Metadata-Version: 2.1
Name: cheonscalculator
Version: 0.0.1
Summary: caculaotion1
Home-page: https://github.com/Cheon31/power
Download-URL: https://github.com/Cheon31/power/archive/refs/heads/main.zip
Author: cheon
License-File: LICENSE
